copro/__init__.py
copro/conflict.py
copro/data.py
copro/evaluation.py
copro/machine_learning.py
copro/models.py
copro/pipeline.py
copro/plots.py
copro/selection.py
copro/utils.py
copro/variables.py
copro/scripts/__init__.py
copro/scripts/copro_runner.py
copro-0.1.2.dist-info/LICENSE
copro-0.1.2.dist-info/METADATA
copro-0.1.2.dist-info/WHEEL
copro-0.1.2.dist-info/entry_points.txt
copro-0.1.2.dist-info/top_level.txt
copro-0.1.2.dist-info/RECORD
